Metadata-Version: 2.1
Name: aplicacion-ventas-beto
Version: 0.1.1
Summary: Aplicacion de ventas, impuestos y descuentos
Home-page: https://github.com/usuario/gestor_ventas
Author: Beto
Author-email: albermontesbre@gmail.com
Classifier: Programming Language :: Python :: 3
Classifier: License :: OSI Approved :: MIT License
Classifier: Operating System :: OS Independent
Requires-Python: >=3.6
License-File: LICENCE
